src/DetectAge.py
src/__init__.py
age_detection_local_python_package-0.0.2.dist-info/LICENSE
age_detection_local_python_package-0.0.2.dist-info/METADATA
age_detection_local_python_package-0.0.2.dist-info/WHEEL
age_detection_local_python_package-0.0.2.dist-info/top_level.txt
age_detection_local_python_package-0.0.2.dist-info/RECORD
