Metadata-Version: 2.1
Name: age-detection-local-python-package
Version: 0.0.2
Summary: PyPI Package for age detection
Home-page: https://github.com/javatechy/dokr
Author: Circles
Author-email: info@circles.zone
Classifier: Programming Language :: Python :: 3
Classifier: License :: Other/Proprietary License
Classifier: Operating System :: OS Independent
License-File: LICENSE
